oaikit/__init__.py
oaikit/base.py
oaikit/completion.py
oaikit/conv.py
oaikit/models.py
oaikit/msg.py
oaikit/oai.py
oaikit/role.py
oaikit/typings.py
oaikit/utils.py
oaikit/content/__init__.py
oaikit/content/image.py
oaikit/content/text.py
oaikit/fn_call/__init__.py
oaikit/fn_call/model.py
oaikit-0.3.0.dist-info/LICENSE
oaikit-0.3.0.dist-info/METADATA
oaikit-0.3.0.dist-info/WHEEL
oaikit-0.3.0.dist-info/top_level.txt
oaikit-0.3.0.dist-info/RECORD
