Metadata-Version: 2.1
Name: oaikit
Version: 0.3.0
Summary: Python wrapper for OpenAI API.
Home-page: https://pypi.org/project/oaikit/
Author: Alejo Prieto Dávalos
Author-email: alejoprietodavalos@gmail.com
Project-URL: Source, https://github.com/AlejoPrietoDavalos/oaikit/
Requires-Python: >=3.11
License-File: LICENSE
Requires-Dist: pydantic >=2.8
Requires-Dist: openai >=1.40.3
Requires-Dist: instructor >=1.3.0
